pygenome/Saccharomyces_cerevisiae.zip
pygenome/__init__.py
pygenome/_data.py
pygenome/_pickle_genes.py
pygenome/_pickle_lists.py
pygenome/_pickle_primers.py
pygenome/_pretty.py
pygenome/_version.py
pygenome/intergenic.py
pygenome/locus.py
pygenome/pFA6a-GFPS65T-kanMX6.gb
pygenome/pFA6a-kanMX4.gb
pygenome/sg.py
pygenome/standard_name.py
pygenome/systematic_name.py
pygenome/update.py
pygenome-3.1.0.dist-info/LICENSE.txt
pygenome-3.1.0.dist-info/METADATA
pygenome-3.1.0.dist-info/WHEEL
pygenome-3.1.0.dist-info/top_level.txt
pygenome-3.1.0.dist-info/RECORD
