Metadata-Version: 2.1
Name: pygenome
Version: 3.1.0
Summary: Accessing the Saccharomyces cerevisiae genome from Python
Home-page: https://github.com/BjornFJohansson/pygenome
Author: Björn Johansson
Author-email: bjorn_johansson@bio.uminho.pt
License: LICENSE.txt
Keywords: bioinformatics
Platform: UNKNOWN
Classifier: Development Status :: 4 - Beta
Classifier: Environment :: Console
Classifier: Intended Audience :: Education
Classifier: Intended Audience :: Developers
Classifier: Intended Audience :: Science/Research
Classifier: License :: OSI Approved :: BSD License
Classifier: Programming Language :: Python :: 3.6
Classifier: Programming Language :: Python :: 3.7
Classifier: Programming Language :: Python :: 3.8
Classifier: Topic :: Education
Classifier: Topic :: Scientific/Engineering :: Bio-Informatics
Requires-Dist: pydna
Requires-Dist: appdirs
Requires-Dist: tqdm
Requires-Dist: requests
Requires-Dist: prettytable
